LICENSE
nonebot_plugin_appinsights/__init__.py
nonebot_plugin_appinsights/config.py
nonebot_plugin_appinsights-0.2.0.dist-info/LICENSE
nonebot_plugin_appinsights-0.2.0.dist-info/METADATA
nonebot_plugin_appinsights-0.2.0.dist-info/WHEEL
nonebot_plugin_appinsights-0.2.0.dist-info/RECORD
