Metadata-Version: 2.1
Name: nonebot-plugin-appinsights
Version: 0.2.0
Summary: 
License: AGPLv3
Author: XZhouQD
Author-email: X.Zhou.QD@hotmail.com
Requires-Python: >=3.8.0,<4.0.0
Classifier: License :: Other/Proprietary License
Classifier: Programming Language :: Python :: 3
Classifier: Programming Language :: Python :: 3.8
Classifier: Programming Language :: Python :: 3.9
Classifier: Programming Language :: Python :: 3.10
Classifier: Programming Language :: Python :: 3.11
Requires-Dist: nonebot2 (>=2.0.0,<3.0.0)
Requires-Dist: opencensus-ext-azure (>=1.1.9,<2.0.0)
Requires-Dist: requests (<2.30.0)
